ppu/__init__.py
ppu/__version__.py
ppu/find_executable.py
ppu-0.8.0.data/scripts/cmp.py
ppu-0.8.0.data/scripts/remove-old-files.py
ppu-0.8.0.data/scripts/rm.py
ppu-0.8.0.data/scripts/which.py
ppu-0.8.0.dist-info/METADATA
ppu-0.8.0.dist-info/RECORD
ppu-0.8.0.dist-info/WHEEL
ppu-0.8.0.dist-info/top_level.txt
